mklicense/__init__.py
mklicense/__main__.py
mklicense/app.py
mklicense/factory.py
mklicense/license.py
mklicense/licenses/AGPL3.txt
mklicense/licenses/Apache2.txt
mklicense/licenses/BSD0.txt
mklicense/licenses/BSD1.txt
mklicense/licenses/BSD2.txt
mklicense/licenses/BSD3.txt
mklicense/licenses/BSD4.txt
mklicense/licenses/BSL.txt
mklicense/licenses/GPL3.txt
mklicense/licenses/LGPL3.txt
mklicense/licenses/MIT.txt
mklicense/licenses/MPL2.txt
mklicense/licenses/Unlicense.txt
mklicense/licenses/WTFPL.txt
mklicense/parser.py
mklicense/py.typed
mklicense-0.3.0.dist-info/LICENSE.txt
mklicense-0.3.0.dist-info/METADATA
mklicense-0.3.0.dist-info/WHEEL
mklicense-0.3.0.dist-info/entry_points.txt
mklicense-0.3.0.dist-info/RECORD
