Metadata-Version: 2.3
Name: mklicense
Version: 0.3.0
Summary: Quickly generate a license file
Author: Jonas da Silva
Author-email: phoenixr41414141@gmail.com
Requires-Python: <4,>=3.13
Classifier: Development Status :: 5 - Production/Stable
Classifier: Environment :: Console
Classifier: License :: OSI Approved :: MIT License
Classifier: Natural Language :: English
Classifier: Programming Language :: Python
Classifier: Programming Language :: Python :: 3
Classifier: Programming Language :: Python :: 3 :: Only
Classifier: Topic :: Utilities
Classifier: Typing :: Typed
Provides-Extra: dev
Requires-Dist: attrs (==24.3.0)
Requires-Dist: mypy (>=1.14.1) ; extra == "dev"
Requires-Dist: platformdirs (>=4.3.6,<5.0.0)
Requires-Dist: textual (==1.0.0)
Project-URL: Bug Tracker, https://github.com/phoenixr-codes/mklicense/issues
Project-URL: Repository, https://github.com/phoenixr-codes/mklicense
